http_nt_pclient/__init__.py
http_nt_pclient/api_client.py
http_nt_pclient/configuration.py
http_nt_pclient/rest.py
http_nt_pclient/api/__init__.py
http_nt_pclient/api/general_api.py
http_nt_pclient/api/strategy_api.py
http_nt_pclient/api/twap_api.py
http_nt_pclient/models/__init__.py
http_nt_pclient/models/account.py
http_nt_pclient/models/api_error.py
http_nt_pclient/models/execution_id.py
http_nt_pclient/models/execution_ids.py
http_nt_pclient/models/exposure_dto.py
http_nt_pclient/models/instrument_quantities_definition.py
http_nt_pclient/models/instrument_specification.py
http_nt_pclient/models/issue.py
http_nt_pclient/models/limit_breached_info.py
http_nt_pclient/models/limit_response.py
http_nt_pclient/models/metrics.py
http_nt_pclient/models/multiple_strategies_action_request.py
http_nt_pclient/models/multiple_twap_parameters.py
http_nt_pclient/models/multiple_twap_update_parameters.py
http_nt_pclient/models/position_dtov2.py
http_nt_pclient/models/requested_action.py
http_nt_pclient/models/response.py
http_nt_pclient/models/risk.py
http_nt_pclient/models/risk_response.py
http_nt_pclient/models/sites.py
http_nt_pclient/models/strategies.py
http_nt_pclient/models/strategy_state.py
http_nt_pclient/models/trade.py
http_nt_pclient/models/twap.py
http_nt_pclient/models/twap_create_controller_response.py
http_nt_pclient/models/twap_parameters.py
http_nt_pclient/models/twap_parameters_with_id.py
http_nt_pclient/models/twap_parameters_with_id_and_statistics.py
http_nt_pclient/models/twap_parameters_with_statistics.py
http_nt_pclient/models/twap_replace.py
http_nt_pclient/models/twap_replace_controller_response.py
http_nt_pclient/models/twap_replace_response.py
http_nt_pclient/models/twap_statistics.py
http_nt_pclient/models/twap_update_controller_response.py
http_nt_pclient/models/twap_update_parameters.py
http_nt_pclient/models/twap_update_parameters_with_id.py
http_nt_pclient/models/twap_with_statistics.py
http_nt_pclient-1.1.0.dist-info/METADATA
http_nt_pclient-1.1.0.dist-info/WHEEL
http_nt_pclient-1.1.0.dist-info/top_level.txt
http_nt_pclient-1.1.0.dist-info/RECORD
