Metadata-Version: 2.4
Name: http_nt_pclient
Version: 1.1.0
Summary: Nickel Trader API
Home-page: 
Author-email: 
Keywords: Swagger,Nickel Trader API
Requires-Python: >=3.10
Requires-Dist: urllib3>=1.15
Requires-Dist: six>=1.10
Requires-Dist: certifi
Requires-Dist: python-dateutil
Requires-Dist: aiohttp
Dynamic: description
Dynamic: keywords
Dynamic: requires-dist
Dynamic: requires-python
Dynamic: summary
